{
  "db_name": "PostgreSQL",
  "query": "\n            SELECT id, fetched_at, item_id, name, payload\n            FROM item_snapshots\n            WHERE item_id = $1\n            ORDER BY fetched_at DESC\n            LIMIT 1\n            ",
  "describe": {
    "columns": [
      {
        "ordinal": 0,
        "name": "id",
        "type_info": "Int8"
      },
      {
        "ordinal": 1,
        "name": "fetched_at",
        "type_info": "Timestamptz"
      },
      {
        "ordinal": 2,
        "name": "item_id",
        "type_info": "Int8"
      },
      {
        "ordinal": 3,
        "name": "name",
        "type_info": "Text"
      },
      {
        "ordinal": 4,
        "name": "payload",
        "type_info": "Jsonb"
      }
    ],
    "parameters": {
      "Left": [
        "Int8"
      ]
    },
    "nullable": [
      false,
      false,
      false,
      false,
      false
    ]
  },
  "hash": "0e29c741e9c0f67c3c0c748fdb492c0f72d1fe9360b1b9f85d0ddf355e99a52e"
}
